graphs/hypothesis-tested-brightgreen.svg
pyrle/__init__.py
pyrle/methods.py
pyrle/rle.py
pyrle/rledict.py
pyrle/src/__init__.py
pyrle/src/coverage.c
pyrle/src/coverage.cp311-win_amd64.pyd
pyrle/src/coverage.pyx
pyrle/src/getitem.c
pyrle/src/getitem.cp311-win_amd64.pyd
pyrle/src/getitem.pyx
pyrle/src/rle.c
pyrle/src/rle.cp311-win_amd64.pyd
pyrle/src/rle.pyx
tests/__init__.py
tests/compute_Rle.R
tests/compute_coverage.R
tests/helpers.py
tests/hypothesis_helper.py
tests/subset_coverage.R
tests/test_hypothesis.py
tests/test_hypothesis_coverage.py
tests/test_subset_coverage.py
pyrle-0.0.42.dist-info/LICENSE
pyrle-0.0.42.dist-info/METADATA
pyrle-0.0.42.dist-info/WHEEL
pyrle-0.0.42.dist-info/top_level.txt
pyrle-0.0.42.dist-info/RECORD
