Metadata-Version: 2.2
Name: pyrle
Version: 0.0.42
Summary: Numeric run length encoding for Python.
Author-email: Endre Bakken Stovner <endbak@pm.me>
License: MIT
Project-URL: Homepage, http://github.com/pyranges/pyrle
Keywords: run-lengths,Rle,genomics
Classifier: Programming Language :: Python :: 3
Classifier: Development Status :: 4 - Beta
Classifier: Environment :: Other Environment
Classifier: Intended Audience :: Developers
Classifier: Intended Audience :: Science/Research
Classifier: License :: OSI Approved :: MIT License
Classifier: Operating System :: POSIX :: Linux
Classifier: Operating System :: MacOS :: MacOS X
Classifier: Topic :: Scientific/Engineering
License-File: LICENSE
Requires-Dist: pandas
Requires-Dist: tabulate
Requires-Dist: numpy
Requires-Dist: natsort
Provides-Extra: dev
Requires-Dist: black; extra == "dev"
Requires-Dist: bumpver; extra == "dev"
Requires-Dist: isort; extra == "dev"
Requires-Dist: pip-tools; extra == "dev"
Requires-Dist: pytest; extra == "dev"
